mmct/__init__.py
mmct/core.py
mmct-1.1.3.dist-info/LICENSE
mmct-1.1.3.dist-info/METADATA
mmct-1.1.3.dist-info/WHEEL
mmct-1.1.3.dist-info/top_level.txt
mmct-1.1.3.dist-info/RECORD
