Metadata-Version: 2.1
Name: mmct
Version: 1.1.3
Summary: Multinomial Monte Carlo testing
Home-page: https://github.com/cwand/mmct
Author: Chris Walther Andersen
Author-email: cvvand@gmail.com
Project-URL: Bug Tracker, https://github.com/cwand/mmct/issues
Classifier: Programming Language :: Python :: 3
Classifier: License :: OSI Approved :: MIT License
Classifier: Operating System :: OS Independent
Requires-Python: >=3.8
License-File: LICENSE
Requires-Dist: numpy (>=1.20)
Requires-Dist: scipy (>=1.7)
Provides-Extra: testing
Requires-Dist: pytest (>=6.0) ; extra == 'testing'
Requires-Dist: pytest-cov (>=2.0) ; extra == 'testing'
Requires-Dist: mypy (>=0.910) ; extra == 'testing'
Requires-Dist: flake8 (>=3.9) ; extra == 'testing'
Requires-Dist: tox (>=3.24) ; extra == 'testing'
